MANIFEST.in
README.rst
setup.cfg
setup.py
Trionyx.egg-info/PKG-INFO
Trionyx.egg-info/SOURCES.txt
Trionyx.egg-info/dependency_links.txt
Trionyx.egg-info/requires.txt
Trionyx.egg-info/top_level.txt
trionyx/__init__.py
trionyx/celery.py
trionyx/config.py
trionyx/layout.py
trionyx/log.py
trionyx/menu.py
trionyx/models.py
trionyx/renderer.py
trionyx/settings.py
trionyx/signals.py
trionyx/tasks.py
trionyx/urls.py
trionyx/utils.py
trionyx/widgets.py
trionyx/api/__init__.py
trionyx/api/filters.py
trionyx/api/pagination.py
trionyx/api/routers.py
trionyx/api/serializers.py
trionyx/bin/trionyx
trionyx/contrib/__init__.py
trionyx/data/__init__.py
trionyx/data/countries.py
trionyx/data/currencies.py
trionyx/data/timezones.py
trionyx/forms/__init__.py
trionyx/forms/helper.py
trionyx/forms/layout.py
trionyx/quickstart/__init__.py
trionyx/quickstart/__pycache__/__init__.cpython-36.pyc
trionyx/quickstart/ansible/README.rst
trionyx/quickstart/ansible/playbook.yml
trionyx/quickstart/ansible/production
trionyx/quickstart/ansible/requirements.yml
trionyx/quickstart/ansible/upgrade.yml
trionyx/quickstart/ansible/group_vars/all.yml
trionyx/quickstart/ansible/templates/environment.json.j2
trionyx/quickstart/app/__init__.py
trionyx/quickstart/app/apps.py
trionyx/quickstart/app/layouts.py
trionyx/quickstart/app/models.py
trionyx/quickstart/app/migrations/__init__.py
trionyx/quickstart/project/.gitignore
trionyx/quickstart/project/CHANGELOG.rst
trionyx/quickstart/project/Makefile
trionyx/quickstart/project/README.rst
trionyx/quickstart/project/celery_app.py
trionyx/quickstart/project/environment.json
trionyx/quickstart/project/manage.py
trionyx/quickstart/project/requirements-dev.txt
trionyx/quickstart/project/requirements.txt
trionyx/quickstart/project/setup.cfg
trionyx/quickstart/project/wsgi.py
trionyx/quickstart/project/apps/__init__.py
trionyx/quickstart/project/config/__init__.py
trionyx/quickstart/project/config/urls.py
trionyx/quickstart/project/config/settings/__init__.py
trionyx/quickstart/project/config/settings/base.py
trionyx/quickstart/project/config/settings/dev.py
trionyx/quickstart/project/config/settings/live.py
