Metadata-Version: 2.1
Name: Trionyx
Version: 3.0.0
Summary: Trionyx is an application framework for managing data and processes
Home-page: https://github.com/krukas/Trionyx
Author: Maikel Martens
Author-email: maikel@martens.me
License: GPL3
Download-URL: https://github.com/krukas/Trionyx/releases/tag/3.0.0
Keywords: Django,Trionyx,framework,admin,data,processes,application,stack
Platform: UNKNOWN
Classifier: License :: OSI Approved :: GNU General Public License v3 (GPLv3)
Classifier: Programming Language :: Python :: 3
Classifier: Framework :: Django
Requires-Python: ~=3.6
Provides-Extra: dev
